flow/pinn_utilities.py
flow/plotting_results.py
pore2chip/__init__.py
pore2chip/coordination.py
pore2chip/export.py
pore2chip/filter_im.py
pore2chip/generate.py
pore2chip/generate2.py
pore2chip/io.py
pore2chip/metrics.py
pore2chip-0.2.0.dist-info/licenses/LICENSE.md
pore2chip-0.2.0.dist-info/METADATA
pore2chip-0.2.0.dist-info/WHEEL
pore2chip-0.2.0.dist-info/top_level.txt
pore2chip-0.2.0.dist-info/RECORD
