Metadata-Version: 2.4
Name: pore2chip
Version: 0.2.0
Summary: A package that takes 3D images of porous materials and generates representative micromodels
Author-email: Aramy Truong <aramy.truong@pnnl.gov>, Maruti Mudunuru <maruti@pnnl.gov>, Erin Rooney <erin.rooney@usda.gov>, Arunima Bhattacharjee <arunimab@pnnl.gov>, Tamas Varga <tamas.varga@pnnl.gov>, Lal Mamud <lal.mamud@pnnl.gov>, "Xiaoliang (Bryan) He" <xiaoliang.he@pnnl.gov>, Anil Krishna Battu <anilkrishna.battu@gmail.com>, Satish Karra <karra@pnnl.gov>
Project-URL: Homepage, https://www.emsl.pnnl.gov/science/instruments-resources/terraforms-pore2chip
Project-URL: Source, https://github.com/EMSL-Computing/Pore2Chip
Classifier: Programming Language :: Python :: 3
Classifier: Operating System :: OS Independent
Requires-Python: >=3.9
License-File: LICENSE.md
Requires-Dist: drawsvg
Requires-Dist: ezdxf
Requires-Dist: feret
Requires-Dist: numpy
Requires-Dist: opencv-python
Requires-Dist: openpnm
Requires-Dist: porespy
Requires-Dist: scikit-image
Requires-Dist: scipy
Requires-Dist: yapf
Requires-Dist: svglib
Requires-Dist: reportlab==3.6.13
Requires-Dist: cairosvg
Requires-Dist: gstools
Requires-Dist: jaxlib
Requires-Dist: jax
Requires-Dist: optax
Requires-Dist: matplotlib
Provides-Extra: extras
Requires-Dist: pypardiso; extra == "extras"
Dynamic: license-file
